metalm_tools/__init__.py
metalm_tools/code_interpreter/codeinterpreter_session.py
metalm_tools/code_interpreter/tool.py
metalm_tools-0.1.2.dist-info/LICENSE
metalm_tools-0.1.2.dist-info/METADATA
metalm_tools-0.1.2.dist-info/WHEEL
metalm_tools-0.1.2.dist-info/RECORD
