Metadata-Version: 2.1
Name: metalm-tools
Version: 0.1.2
Summary: MetaLM工具集
Author: 陈立成
Author-email: jueyuan.clc@xuelangyun.com
Requires-Python: >=3.10,<4.0
Classifier: Programming Language :: Python :: 3
Classifier: Programming Language :: Python :: 3.10
Classifier: Programming Language :: Python :: 3.11
Classifier: Programming Language :: Python :: 3.12
Requires-Dist: langchain-community (>=0.2.12,<0.3.0)
Requires-Dist: langchain-core (>=0.2.33,<0.3.0)
Requires-Dist: poetry2setup (>=1.1.0,<2.0.0)
Requires-Dist: requests (>=2.32.3,<3.0.0)
